[{"id":2,"type":"Flaque","typeId":45,"team":"aliens","creaTurn":0,"loc":"zone","locId":0,"tileId":1321,"oldTileId":1321,"squadsLeft":6,"damage":0,"camoAP":-1,"eq":"aucun","prt":"aucune","armor":4,"ap":8,"apLeft":8,"oldapLeft":8,"salvoLeft":0,"ammo":"none","ammo2":"none","vet":0,"xp":0,"range":0,"sort":0,"army":0,"tags":[]},{"id":4,"type":"Veilleurs","typeId":44,"team":"aliens","creaTurn":0,"loc":"zone","locId":0,"tileId":1140,"oldTileId":1140,"squadsLeft":4,"damage":0,"camoAP":-1,"eq":"aucun","prt":"aucune","armor":2,"ap":30,"apLeft":30,"oldapLeft":30,"salvoLeft":1,"ammo":"ruche","ammo2":"ruche","vet":0,"xp":0,"range":6,"sort":60,"army":0,"tags":["invisible"]},{"id":6,"type":"Veilleurs","typeId":44,"team":"aliens","creaTurn":0,"loc":"zone","locId":0,"tileId":1261,"oldTileId":1261,"squadsLeft":4,"damage":0,"camoAP":-1,"eq":"aucun","prt":"aucune","armor":2,"ap":30,"apLeft":30,"oldapLeft":30,"salvoLeft":1,"ammo":"ruche","ammo2":"ruche","vet":0,"xp":0,"range":6,"sort":60,"army":0,"tags":["invisible"]},{"id":12,"type":"Volcan","typeId":37,"team":"aliens","creaTurn":18,"loc":"zone","locId":0,"tileId":2733,"oldTileId":2733,"squadsLeft":6,"damage":0,"camoAP":-1,"eq":"aucun","prt":"aucune","armor":12,"ap":16,"apLeft":16,"oldapLeft":16,"salvoLeft":1,"ammo":"feu","ammo2":"feu","vet":0,"xp":0,"range":4,"sort":40,"army":0,"tags":["bug"]},{"id":18,"type":"Ruche","typeId":17,"team":"aliens","creaTurn":25,"loc":"zone","locId":0,"tileId":2997,"oldTileId":2997,"squadsLeft":6,"damage":0,"camoAP":-1,"eq":"aucun","prt":"aucune","armor":5,"ap":16,"apLeft":16,"oldapLeft":16,"salvoLeft":1,"ammo":"ruche","ammo2":"ruche","vet":0,"xp":0,"range":4,"sort":40,"army":0,"tags":["bug"]},{"id":46,"type":"Asticots","typeId":9,"team":"aliens","creaTurn":28,"loc":"zone","locId":0,"tileId":2597,"oldTileId":2536,"squadsLeft":8,"damage":0,"camoAP":-1,"eq":"aucun","prt":"aucune","armor":0,"ap":6,"apLeft":0.2999999999999998,"oldapLeft":6,"salvoLeft":1,"ammo":"creuseur","ammo2":"none","vet":0,"xp":0,"range":0,"sort":0,"army":0,"tags":[]},{"id":50,"type":"Volcan","typeId":37,"team":"aliens","creaTurn":28,"loc":"zone","locId":0,"tileId":2895,"oldTileId":2895,"squadsLeft":6,"damage":0,"camoAP":-1,"eq":"aucun","prt":"aucune","armor":12,"ap":16,"apLeft":16,"oldapLeft":16,"salvoLeft":1,"ammo":"feu","ammo2":"feu","vet":0,"xp":0,"range":4,"sort":40,"army":0,"tags":["larve"]},{"id":58,"type":"Asticots","typeId":9,"team":"aliens","creaTurn":30,"loc":"zone","locId":0,"tileId":2659,"oldTileId":2658,"squadsLeft":8,"damage":0,"camoAP":-1,"eq":"aucun","prt":"aucune","armor":0,"ap":6,"apLeft":0,"oldapLeft":6,"salvoLeft":1,"ammo":"creuseur","ammo2":"none","vet":0,"xp":0,"range":0,"sort":0,"army":0,"tags":[]},{"id":62,"type":"Asticots","typeId":9,"team":"aliens","creaTurn":30,"loc":"zone","locId":0,"tileId":1274,"oldTileId":1213,"squadsLeft":8,"damage":0,"camoAP":-1,"eq":"aucun","prt":"aucune","armor":0,"ap":6,"apLeft":0.1999999999999993,"oldapLeft":4.499999999999999,"salvoLeft":1,"ammo":"creuseur","ammo2":"none","vet":0,"xp":0,"range":0,"sort":0,"army":0,"tags":[]},{"id":63,"type":"Vers","typeId":40,"team":"aliens","creaTurn":30,"loc":"zone","locId":0,"tileId":1394,"oldTileId":1335,"squadsLeft":8,"damage":0,"camoAP":-1,"eq":"aucun","prt":"aucune","armor":0,"ap":6,"apLeft":-1,"oldapLeft":4.7,"salvoLeft":1,"ammo":"creuseur","ammo2":"none","vet":0,"xp":0,"range":0,"sort":0,"army":0,"tags":[]},{"id":64,"type":"Asticots","typeId":9,"team":"aliens","creaTurn":31,"loc":"zone","locId":0,"tileId":2535,"oldTileId":2594,"squadsLeft":8,"damage":0,"camoAP":-1,"eq":"aucun","prt":"aucune","armor":0,"ap":6,"apLeft":0.2999999999999998,"oldapLeft":6,"salvoLeft":1,"ammo":"creuseur","ammo2":"none","vet":0,"xp":0,"range":0,"sort":0,"army":0,"tags":[]},{"id":73,"type":"Volcan","typeId":37,"team":"aliens","creaTurn":32,"loc":"zone","locId":0,"tileId":3065,"oldTileId":3065,"squadsLeft":6,"damage":0,"camoAP":-1,"eq":"aucun","prt":"aucune","armor":12,"ap":16,"apLeft":16,"oldapLeft":16,"salvoLeft":1,"ammo":"feu","ammo2":"feu","vet":0,"xp":0,"range":4,"sort":40,"army":0,"tags":["bug"]},{"id":74,"type":"Larves","typeId":14,"team":"aliens","creaTurn":32,"loc":"zone","locId":0,"tileId":1450,"oldTileId":1390,"squadsLeft":4,"damage":0,"camoAP":-1,"eq":"aucun","prt":"aucune","armor":1,"ap":12,"apLeft":-3.9000000000000004,"oldapLeft":12,"salvoLeft":1,"ammo":"none","ammo2":"none","vet":0,"xp":0,"range":0,"sort":0,"army":0,"tags":[]},{"id":75,"type":"Asticots","typeId":9,"team":"aliens","creaTurn":33,"loc":"zone","locId":0,"tileId":2536,"oldTileId":2595,"squadsLeft":8,"damage":0,"camoAP":-1,"eq":"aucun","prt":"aucune","armor":0,"ap":6,"apLeft":-2.7,"oldapLeft":5.3,"salvoLeft":1,"ammo":"creuseur","ammo2":"none","vet":0,"xp":0,"range":0,"sort":0,"army":0,"tags":[]},{"id":77,"type":"Vers","typeId":40,"team":"aliens","creaTurn":33,"loc":"zone","locId":0,"tileId":1330,"oldTileId":1271,"squadsLeft":8,"damage":0,"camoAP":-1,"eq":"aucun","prt":"aucune","armor":0,"ap":6,"apLeft":0.10000000000000053,"oldapLeft":5.800000000000001,"salvoLeft":1,"ammo":"creuseur","ammo2":"none","vet":0,"xp":0,"range":0,"sort":0,"army":0,"tags":[]},{"id":81,"type":"Asticots","typeId":9,"team":"aliens","creaTurn":34,"loc":"zone","locId":0,"tileId":2595,"oldTileId":2534,"squadsLeft":8,"damage":0,"camoAP":-1,"eq":"aucun","prt":"aucune","armor":0,"ap":6,"apLeft":0.2999999999999998,"oldapLeft":6,"salvoLeft":1,"ammo":"creuseur","ammo2":"none","vet":0,"xp":0,"range":0,"sort":0,"army":0,"tags":[]},{"id":82,"type":"Vers","typeId":40,"team":"aliens","creaTurn":34,"loc":"zone","locId":0,"tileId":2654,"oldTileId":2593,"squadsLeft":8,"damage":0,"camoAP":-1,"eq":"aucun","prt":"aucune","armor":0,"ap":6,"apLeft":-2.3,"oldapLeft":2,"salvoLeft":1,"ammo":"creuseur","ammo2":"none","vet":0,"xp":0,"range":0,"sort":0,"army":0,"tags":[]},{"id":84,"type":"Asticots","typeId":9,"team":"aliens","creaTurn":34,"loc":"zone","locId":0,"tileId":2533,"oldTileId":2653,"squadsLeft":8,"damage":0,"camoAP":-1,"eq":"aucun","prt":"aucune","armor":0,"ap":6,"apLeft":-1,"oldapLeft":6,"salvoLeft":1,"ammo":"creuseur","ammo2":"none","vet":0,"xp":0,"range":0,"sort":0,"army":0,"tags":[]},{"id":88,"type":"Asticots","typeId":9,"team":"aliens","creaTurn":35,"loc":"zone","locId":0,"tileId":2596,"oldTileId":2655,"squadsLeft":8,"damage":0,"camoAP":-1,"eq":"aucun","prt":"aucune","armor":0,"ap":6,"apLeft":-2.1000000000000005,"oldapLeft":3.5999999999999996,"salvoLeft":1,"ammo":"creuseur","ammo2":"none","vet":0,"xp":0,"range":0,"sort":0,"army":0,"tags":[]},{"id":89,"type":"Asticots","typeId":9,"team":"aliens","creaTurn":35,"loc":"zone","locId":0,"tileId":2714,"oldTileId":2774,"squadsLeft":8,"damage":0,"camoAP":-1,"eq":"aucun","prt":"aucune","armor":0,"ap":6,"apLeft":-4.7,"oldapLeft":5,"salvoLeft":1,"ammo":"creuseur","ammo2":"none","vet":0,"xp":0,"range":0,"sort":0,"army":0,"tags":[]},{"id":90,"type":"Asticots","typeId":9,"team":"aliens","creaTurn":35,"loc":"zone","locId":0,"tileId":1209,"oldTileId":1089,"squadsLeft":8,"damage":0,"camoAP":-1,"eq":"aucun","prt":"aucune","armor":0,"ap":6,"apLeft":-2.8999999999999995,"oldapLeft":5.7,"salvoLeft":1,"ammo":"creuseur","ammo2":"none","vet":0,"xp":0,"range":0,"sort":0,"army":0,"tags":[]},{"id":91,"type":"Vers","typeId":40,"team":"aliens","creaTurn":35,"loc":"zone","locId":0,"tileId":1152,"oldTileId":1032,"squadsLeft":8,"damage":0,"camoAP":-1,"eq":"aucun","prt":"aucune","armor":0,"ap":6,"apLeft":-4.4,"oldapLeft":5.6,"salvoLeft":1,"ammo":"creuseur","ammo2":"none","vet":0,"xp":0,"range":0,"sort":0,"army":0,"tags":[]},{"id":92,"type":"Larves","typeId":14,"team":"aliens","creaTurn":35,"loc":"zone","locId":0,"tileId":1335,"oldTileId":1276,"squadsLeft":4,"damage":0,"camoAP":-1,"eq":"aucun","prt":"aucune","armor":1,"ap":12,"apLeft":-4.9,"oldapLeft":3.5999999999999996,"salvoLeft":1,"ammo":"none","ammo2":"none","vet":0,"xp":0,"range":0,"sort":0,"army":0,"tags":[]},{"id":93,"type":"Ruche","typeId":17,"team":"aliens","creaTurn":36,"loc":"zone","locId":0,"tileId":3488,"oldTileId":3488,"squadsLeft":6,"damage":0,"camoAP":-1,"eq":"aucun","prt":"aucune","armor":5,"ap":16,"apLeft":16,"oldapLeft":16,"salvoLeft":1,"ammo":"ruche","ammo2":"ruche","vet":0,"xp":0,"range":4,"sort":40,"army":0,"tags":["larve"]},{"id":95,"type":"Asticots","typeId":9,"team":"aliens","creaTurn":36,"loc":"zone","locId":0,"tileId":1206,"oldTileId":1145,"squadsLeft":8,"damage":0,"camoAP":-1,"eq":"aucun","prt":"aucune","armor":0,"ap":6,"apLeft":-1.200000000000001,"oldapLeft":4.499999999999999,"salvoLeft":1,"ammo":"creuseur","ammo2":"none","vet":0,"xp":0,"range":0,"sort":0,"army":0,"tags":[]},{"id":96,"type":"Vers","typeId":40,"team":"aliens","creaTurn":36,"loc":"zone","locId":0,"tileId":1092,"oldTileId":1031,"squadsLeft":8,"damage":0,"camoAP":-1,"eq":"aucun","prt":"aucune","armor":0,"ap":6,"apLeft":-0.2999999999999998,"oldapLeft":5.4,"salvoLeft":1,"ammo":"creuseur","ammo2":"none","vet":0,"xp":0,"range":0,"sort":0,"army":0,"tags":[]},{"id":98,"type":"Asticots","typeId":9,"team":"aliens","creaTurn":36,"loc":"zone","locId":0,"tileId":1327,"oldTileId":1205,"squadsLeft":8,"damage":0,"camoAP":-1,"eq":"aucun","prt":"aucune","armor":0,"ap":6,"apLeft":-3.3,"oldapLeft":5.3,"salvoLeft":1,"ammo":"creuseur","ammo2":"none","vet":0,"xp":0,"range":0,"sort":0,"army":0,"tags":[]},{"id":99,"type":"Oeuf","typeId":6,"team":"aliens","creaTurn":37,"loc":"zone","locId":0,"tileId":496,"oldTileId":496,"squadsLeft":6,"damage":0,"camoAP":-1,"eq":"aucun","prt":"aucune","armor":0,"ap":8,"apLeft":8,"oldapLeft":8,"salvoLeft":0,"ammo":"none","ammo2":"none","vet":0,"xp":0,"range":0,"sort":0,"army":0,"tags":["larve"]},{"id":102,"type":"Asticots","typeId":9,"team":"aliens","creaTurn":37,"loc":"zone","locId":0,"tileId":1389,"oldTileId":1270,"squadsLeft":8,"damage":0,"camoAP":-1,"eq":"aucun","prt":"aucune","armor":0,"ap":6,"apLeft":-1.2999999999999998,"oldapLeft":6,"salvoLeft":1,"ammo":"creuseur","ammo2":"none","vet":0,"xp":0,"range":0,"sort":0,"army":0,"tags":[]},{"id":104,"type":"Ruche","typeId":17,"team":"aliens","creaTurn":38,"loc":"zone","locId":0,"tileId":307,"oldTileId":307,"squadsLeft":6,"damage":0,"camoAP":-1,"eq":"aucun","prt":"aucune","armor":5,"ap":16,"apLeft":16,"oldapLeft":16,"salvoLeft":1,"ammo":"ruche","ammo2":"ruche","vet":0,"xp":0,"range":4,"sort":40,"army":0,"tags":["larve"]},{"id":105,"type":"Asticots","typeId":9,"team":"aliens","creaTurn":38,"loc":"zone","locId":0,"tileId":2892,"oldTileId":2891,"squadsLeft":8,"damage":0,"camoAP":-1,"eq":"aucun","prt":"aucune","armor":0,"ap":6,"apLeft":0.7000000000000002,"oldapLeft":3.7,"salvoLeft":1,"ammo":"creuseur","ammo2":"none","vet":0,"xp":0,"range":0,"sort":0,"army":0,"tags":[]},{"id":107,"type":"Asticots","typeId":9,"team":"aliens","creaTurn":39,"loc":"zone","locId":0,"tileId":1157,"oldTileId":1098,"squadsLeft":8,"damage":0,"camoAP":-1,"eq":"aucun","prt":"aucune","armor":0,"ap":6,"apLeft":-1.8999999999999995,"oldapLeft":5.1000000000000005,"salvoLeft":1,"ammo":"creuseur","ammo2":"none","vet":0,"xp":0,"range":0,"sort":0,"army":0,"tags":[]},{"id":109,"type":"Vers","typeId":40,"team":"aliens","creaTurn":39,"loc":"zone","locId":0,"tileId":908,"oldTileId":906,"squadsLeft":8,"damage":0,"camoAP":-1,"eq":"aucun","prt":"aucune","armor":0,"ap":6,"apLeft":-1,"oldapLeft":6,"salvoLeft":1,"ammo":"creuseur","ammo2":"none","vet":0,"xp":0,"range":0,"sort":0,"army":0,"tags":[]},{"id":113,"type":"Asticots","typeId":9,"team":"aliens","creaTurn":40,"loc":"zone","locId":0,"tileId":1100,"oldTileId":980,"squadsLeft":8,"damage":0,"camoAP":-1,"eq":"aucun","prt":"aucune","armor":0,"ap":6,"apLeft":-1,"oldapLeft":6,"salvoLeft":1,"ammo":"creuseur","ammo2":"none","vet":0,"xp":0,"range":0,"sort":0,"army":0,"tags":[]},{"id":117,"type":"Escarbots","typeId":16,"team":"aliens","creaTurn":41,"loc":"zone","locId":0,"tileId":2860,"oldTileId":2680,"squadsLeft":4,"damage":0,"camoAP":-1,"eq":"aucun","prt":"aucune","armor":8,"ap":14,"apLeft":-2.1000000000000005,"oldapLeft":13.799999999999999,"salvoLeft":1,"ammo":"creuseur","ammo2":"none","vet":0,"xp":0,"range":0,"sort":0,"army":0,"tags":[]},{"id":118,"type":"Asticots","typeId":9,"team":"aliens","creaTurn":41,"loc":"zone","locId":0,"tileId":2953,"oldTileId":3013,"squadsLeft":8,"damage":0,"camoAP":-1,"eq":"aucun","prt":"aucune","armor":0,"ap":6,"apLeft":-0.7000000000000002,"oldapLeft":2.3,"salvoLeft":1,"ammo":"creuseur","ammo2":"none","vet":0,"xp":0,"range":0,"sort":0,"army":0,"tags":[]},{"id":119,"type":"Vers","typeId":40,"team":"aliens","creaTurn":41,"loc":"zone","locId":0,"tileId":1032,"oldTileId":973,"squadsLeft":8,"damage":0,"camoAP":-1,"eq":"aucun","prt":"aucune","armor":0,"ap":6,"apLeft":-2.8000000000000007,"oldapLeft":2.8999999999999995,"salvoLeft":1,"ammo":"creuseur","ammo2":"none","vet":0,"xp":0,"range":0,"sort":0,"army":0,"tags":[]},{"id":120,"type":"Asticots","typeId":9,"team":"aliens","creaTurn":41,"loc":"zone","locId":0,"tileId":975,"oldTileId":915,"squadsLeft":8,"damage":0,"camoAP":-1,"eq":"aucun","prt":"aucune","armor":0,"ap":6,"apLeft":-1.2999999999999998,"oldapLeft":6,"salvoLeft":1,"ammo":"creuseur","ammo2":"none","vet":0,"xp":0,"range":0,"sort":0,"army":0,"tags":[]},{"id":121,"type":"Larves","typeId":14,"team":"aliens","creaTurn":41,"loc":"zone","locId":0,"tileId":973,"oldTileId":913,"squadsLeft":4,"damage":0,"camoAP":-1,"eq":"aucun","prt":"aucune","armor":1,"ap":12,"apLeft":0,"oldapLeft":11,"salvoLeft":0,"ammo":"none","ammo2":"none","vet":0,"xp":0,"range":0,"sort":0,"army":0,"tags":[]},{"id":123,"type":"Larves","typeId":14,"team":"aliens","creaTurn":42,"loc":"zone","locId":0,"tileId":854,"oldTileId":735,"squadsLeft":4,"damage":0,"camoAP":-1,"eq":"aucun","prt":"aucune","armor":1,"ap":12,"apLeft":-3.5,"oldapLeft":12,"salvoLeft":1,"ammo":"none","ammo2":"none","vet":0,"xp":0,"range":0,"sort":0,"army":0,"tags":[]},{"id":125,"type":"Wurms","typeId":1,"team":"aliens","creaTurn":42,"loc":"zone","locId":0,"tileId":2665,"oldTileId":2783,"squadsLeft":4,"damage":0,"camoAP":-1,"eq":"aucun","prt":"aucune","armor":3,"ap":18,"apLeft":-11,"oldapLeft":14.6,"salvoLeft":1,"ammo":"none","ammo2":"none","vet":0,"xp":0,"range":0,"sort":0,"army":0,"tags":[""]},{"id":126,"type":"Vers","typeId":40,"team":"aliens","creaTurn":42,"loc":"zone","locId":0,"tileId":791,"oldTileId":671,"squadsLeft":8,"damage":0,"camoAP":-1,"eq":"aucun","prt":"aucune","armor":0,"ap":6,"apLeft":-0.7000000000000002,"oldapLeft":5.3,"salvoLeft":1,"ammo":"creuseur","ammo2":"none","vet":0,"xp":0,"range":0,"sort":0,"army":0,"tags":[]},{"id":128,"type":"Oeuf","typeId":6,"team":"aliens","creaTurn":43,"loc":"zone","locId":0,"tileId":2957,"oldTileId":2957,"squadsLeft":6,"damage":0,"camoAP":-1,"eq":"aucun","prt":"aucune","armor":0,"ap":8,"apLeft":8,"oldapLeft":8,"salvoLeft":0,"ammo":"none","ammo2":"none","vet":0,"xp":0,"range":0,"sort":0,"army":0,"tags":["bug"]},{"id":129,"type":"Vers","typeId":40,"team":"aliens","creaTurn":43,"loc":"zone","locId":0,"tileId":3132,"oldTileId":3192,"squadsLeft":8,"damage":0,"camoAP":-1,"eq":"aucun","prt":"aucune","armor":0,"ap":6,"apLeft":0.40000000000000036,"oldapLeft":3.4000000000000004,"salvoLeft":1,"ammo":"creuseur","ammo2":"none","vet":0,"xp":0,"range":0,"sort":0,"army":0,"tags":[]},{"id":131,"type":"Wurms","typeId":1,"team":"aliens","creaTurn":43,"loc":"zone","locId":0,"tileId":1334,"oldTileId":1214,"squadsLeft":4,"damage":0,"camoAP":-1,"eq":"aucun","prt":"aucune","armor":3,"ap":18,"apLeft":0,"oldapLeft":18,"salvoLeft":0,"ammo":"none","ammo2":"none","vet":0,"xp":0,"range":0,"sort":0,"army":0,"tags":[""]},{"id":132,"type":"Escarbots","typeId":16,"team":"aliens","creaTurn":43,"loc":"zone","locId":0,"tileId":1476,"oldTileId":1297,"squadsLeft":1,"damage":273,"camoAP":-1,"eq":"aucun","prt":"aucune","armor":8,"ap":14,"apLeft":0.5999999999999988,"oldapLeft":10.899999999999999,"salvoLeft":1,"ammo":"creuseur","ammo2":"none","vet":0,"xp":0,"range":0,"sort":0,"army":0,"tags":[]},{"id":133,"type":"Vers","typeId":40,"team":"aliens","creaTurn":44,"loc":"zone","locId":0,"tileId":3314,"oldTileId":3373,"squadsLeft":8,"damage":0,"camoAP":-1,"eq":"aucun","prt":"aucune","armor":0,"ap":6,"apLeft":-2,"oldapLeft":6,"salvoLeft":1,"ammo":"creuseur","ammo2":"none","vet":0,"xp":0,"range":0,"sort":0,"army":0,"tags":[]},{"id":134,"type":"Asticots","typeId":9,"team":"aliens","creaTurn":44,"loc":"zone","locId":0,"tileId":855,"oldTileId":796,"squadsLeft":8,"damage":0,"camoAP":-1,"eq":"aucun","prt":"aucune","armor":0,"ap":6,"apLeft":-2,"oldapLeft":6,"salvoLeft":1,"ammo":"creuseur","ammo2":"none","vet":0,"xp":0,"range":0,"sort":0,"army":0,"tags":[]},{"id":135,"type":"Larves","typeId":14,"team":"aliens","creaTurn":44,"loc":"zone","locId":0,"tileId":1154,"oldTileId":974,"squadsLeft":4,"damage":0,"camoAP":-1,"eq":"aucun","prt":"aucune","armor":1,"ap":12,"apLeft":0,"oldapLeft":11,"salvoLeft":0,"ammo":"none","ammo2":"none","vet":0,"xp":0,"range":0,"sort":0,"army":0,"tags":[]},{"id":136,"type":"Asticots","typeId":9,"team":"aliens","creaTurn":44,"loc":"zone","locId":0,"tileId":735,"oldTileId":674,"squadsLeft":8,"damage":0,"camoAP":-1,"eq":"aucun","prt":"aucune","armor":0,"ap":6,"apLeft":-0.2999999999999998,"oldapLeft":4,"salvoLeft":1,"ammo":"creuseur","ammo2":"none","vet":0,"xp":0,"range":0,"sort":0,"army":0,"tags":[]},{"id":137,"type":"Larves","typeId":14,"team":"aliens","creaTurn":44,"loc":"zone","locId":0,"tileId":612,"oldTileId":493,"squadsLeft":4,"damage":0,"camoAP":-1,"eq":"aucun","prt":"aucune","armor":1,"ap":12,"apLeft":-4.9,"oldapLeft":12,"salvoLeft":1,"ammo":"none","ammo2":"none","vet":0,"xp":0,"range":0,"sort":0,"army":0,"tags":[]},{"id":139,"type":"Bugs","typeId":0,"team":"aliens","creaTurn":44,"loc":"zone","locId":0,"tileId":2720,"oldTileId":2781,"squadsLeft":6,"damage":0,"camoAP":-1,"eq":"aucun","prt":"aucune","armor":4,"ap":14,"apLeft":-7.300000000000001,"oldapLeft":5.5,"salvoLeft":1,"ammo":"creuseur","ammo2":"none","vet":0,"xp":0,"range":0,"sort":0,"army":0,"tags":[]},{"id":141,"type":"Asticots","typeId":9,"team":"aliens","creaTurn":45,"loc":"zone","locId":0,"tileId":794,"oldTileId":734,"squadsLeft":8,"damage":0,"camoAP":-1,"eq":"aucun","prt":"aucune","armor":0,"ap":6,"apLeft":-0.2999999999999998,"oldapLeft":2.7,"salvoLeft":1,"ammo":"creuseur","ammo2":"none","vet":0,"xp":0,"range":0,"sort":0,"army":0,"tags":[]},{"id":142,"type":"Vers","typeId":40,"team":"aliens","creaTurn":45,"loc":"zone","locId":0,"tileId":858,"oldTileId":798,"squadsLeft":8,"damage":0,"camoAP":-1,"eq":"aucun","prt":"aucune","armor":0,"ap":6,"apLeft":-0.40000000000000036,"oldapLeft":2.5999999999999996,"salvoLeft":1,"ammo":"creuseur","ammo2":"none","vet":0,"xp":0,"range":0,"sort":0,"army":0,"tags":[]},{"id":143,"type":"Asticots","typeId":9,"team":"aliens","creaTurn":45,"loc":"zone","locId":0,"tileId":430,"oldTileId":429,"squadsLeft":8,"damage":0,"camoAP":-1,"eq":"aucun","prt":"aucune","armor":0,"ap":6,"apLeft":-0.7000000000000002,"oldapLeft":3.3,"salvoLeft":1,"ammo":"creuseur","ammo2":"none","vet":0,"xp":0,"range":0,"sort":0,"army":0,"tags":[]},{"id":144,"type":"Wurms","typeId":1,"team":"aliens","creaTurn":45,"loc":"zone","locId":0,"tileId":2594,"oldTileId":2713,"squadsLeft":4,"damage":0,"camoAP":-1,"eq":"aucun","prt":"aucune","armor":3,"ap":18,"apLeft":-1.4000000000000004,"oldapLeft":18,"salvoLeft":1,"ammo":"none","ammo2":"none","vet":0,"xp":0,"range":0,"sort":0,"army":0,"tags":[""]},{"id":146,"type":"Punaise","typeId":5,"team":"aliens","creaTurn":45,"loc":"zone","locId":0,"tileId":2655,"oldTileId":2716,"squadsLeft":6,"damage":0,"camoAP":-1,"eq":"aucun","prt":"aucune","armor":3,"ap":16,"apLeft":-3.200000000000003,"oldapLeft":9.599999999999998,"salvoLeft":1,"ammo":"creuseur","ammo2":"none","vet":0,"xp":0,"range":0,"sort":0,"army":0,"tags":[]},{"id":147,"type":"Asticots","typeId":9,"team":"aliens","creaTurn":46,"loc":"zone","locId":0,"tileId":674,"oldTileId":613,"squadsLeft":8,"damage":0,"camoAP":-1,"eq":"aucun","prt":"aucune","armor":0,"ap":6,"apLeft":-2,"oldapLeft":2.3,"salvoLeft":1,"ammo":"creuseur","ammo2":"none","vet":0,"xp":0,"range":0,"sort":0,"army":0,"tags":[]},{"id":148,"type":"Asticots","typeId":9,"team":"aliens","creaTurn":46,"loc":"zone","locId":0,"tileId":554,"oldTileId":494,"squadsLeft":8,"damage":0,"camoAP":-1,"eq":"aucun","prt":"aucune","armor":0,"ap":6,"apLeft":-1.2999999999999998,"oldapLeft":6,"salvoLeft":1,"ammo":"creuseur","ammo2":"none","vet":0,"xp":0,"range":0,"sort":0,"army":0,"tags":[]},{"id":149,"type":"Asticots","typeId":9,"team":"aliens","creaTurn":46,"loc":"zone","locId":0,"tileId":427,"oldTileId":368,"squadsLeft":8,"damage":0,"camoAP":-1,"eq":"aucun","prt":"aucune","armor":0,"ap":6,"apLeft":-0.40000000000000036,"oldapLeft":5.3,"salvoLeft":1,"ammo":"creuseur","ammo2":"none","vet":0,"xp":0,"range":0,"sort":0,"army":0,"tags":[]},{"id":151,"type":"Bugs","typeId":0,"team":"aliens","creaTurn":46,"loc":"zone","locId":0,"tileId":2836,"oldTileId":2897,"squadsLeft":6,"damage":0,"camoAP":-1,"eq":"aucun","prt":"aucune","armor":4,"ap":14,"apLeft":-11.8,"oldapLeft":1,"salvoLeft":1,"ammo":"creuseur","ammo2":"none","vet":0,"xp":0,"range":0,"sort":0,"army":0,"tags":[]},{"id":152,"type":"Vers","typeId":40,"team":"aliens","creaTurn":47,"loc":"zone","locId":0,"tileId":555,"oldTileId":556,"squadsLeft":8,"damage":0,"camoAP":-1,"eq":"aucun","prt":"aucune","armor":0,"ap":6,"apLeft":0.2999999999999998,"oldapLeft":3.3,"salvoLeft":1,"ammo":"creuseur","ammo2":"none","vet":0,"xp":0,"range":0,"sort":0,"army":0,"tags":[]},{"id":153,"type":"Vers","typeId":40,"team":"aliens","creaTurn":47,"loc":"zone","locId":0,"tileId":738,"oldTileId":618,"squadsLeft":8,"damage":0,"camoAP":-1,"eq":"aucun","prt":"aucune","armor":0,"ap":6,"apLeft":-2.5999999999999996,"oldapLeft":6,"salvoLeft":1,"ammo":"creuseur","ammo2":"none","vet":0,"xp":0,"range":0,"sort":0,"army":0,"tags":[]},{"id":154,"type":"Asticots","typeId":9,"team":"aliens","creaTurn":47,"loc":"zone","locId":0,"tileId":736,"oldTileId":675,"squadsLeft":8,"damage":0,"camoAP":-1,"eq":"aucun","prt":"aucune","armor":0,"ap":6,"apLeft":-1.7000000000000002,"oldapLeft":4,"salvoLeft":1,"ammo":"creuseur","ammo2":"none","vet":0,"xp":0,"range":0,"sort":0,"army":0,"tags":[]},{"id":155,"type":"Asticots","typeId":9,"team":"aliens","creaTurn":47,"loc":"zone","locId":0,"tileId":556,"oldTileId":495,"squadsLeft":8,"damage":0,"camoAP":-1,"eq":"aucun","prt":"aucune","armor":0,"ap":6,"apLeft":0.2999999999999998,"oldapLeft":6,"salvoLeft":1,"ammo":"creuseur","ammo2":"none","vet":0,"xp":0,"range":0,"sort":0,"army":0,"tags":[]},{"id":156,"type":"Larves","typeId":14,"team":"aliens","creaTurn":47,"loc":"zone","locId":0,"tileId":432,"oldTileId":370,"squadsLeft":4,"damage":0,"camoAP":-1,"eq":"aucun","prt":"aucune","armor":1,"ap":12,"apLeft":-2.5,"oldapLeft":12,"salvoLeft":1,"ammo":"none","ammo2":"none","vet":0,"xp":0,"range":0,"sort":0,"army":0,"tags":[]},{"id":157,"type":"Bugs","typeId":0,"team":"aliens","creaTurn":47,"loc":"zone","locId":0,"tileId":2776,"oldTileId":2835,"squadsLeft":6,"damage":0,"camoAP":-1,"eq":"aucun","prt":"aucune","armor":4,"ap":14,"apLeft":-1.700000000000001,"oldapLeft":11.1,"salvoLeft":1,"ammo":"creuseur","ammo2":"none","vet":0,"xp":0,"range":0,"sort":0,"army":0,"tags":[]},{"id":158,"type":"Bugs","typeId":0,"team":"aliens","creaTurn":47,"loc":"zone","locId":0,"tileId":2899,"oldTileId":2958,"squadsLeft":6,"damage":0,"camoAP":-1,"eq":"aucun","prt":"aucune","armor":4,"ap":14,"apLeft":-9,"oldapLeft":5.199999999999999,"salvoLeft":1,"ammo":"creuseur","ammo2":"none","vet":0,"xp":0,"range":0,"sort":0,"army":0,"tags":[]},{"id":159,"type":"Larves","typeId":14,"team":"aliens","creaTurn":48,"loc":"zone","locId":0,"tileId":557,"oldTileId":437,"squadsLeft":4,"damage":0,"camoAP":-1,"eq":"aucun","prt":"aucune","armor":1,"ap":12,"apLeft":-2,"oldapLeft":12,"salvoLeft":1,"ammo":"none","ammo2":"none","vet":0,"xp":0,"range":0,"sort":0,"army":0,"tags":[]},{"id":160,"type":"Asticots","typeId":9,"team":"aliens","creaTurn":48,"loc":"zone","locId":0,"tileId":495,"oldTileId":436,"squadsLeft":8,"damage":0,"camoAP":-1,"eq":"aucun","prt":"aucune","armor":0,"ap":6,"apLeft":0,"oldapLeft":6,"salvoLeft":1,"ammo":"creuseur","ammo2":"none","vet":0,"xp":0,"range":0,"sort":0,"army":0,"tags":[]},{"id":161,"type":"Asticots","typeId":9,"team":"aliens","creaTurn":48,"loc":"zone","locId":0,"tileId":249,"oldTileId":247,"squadsLeft":8,"damage":0,"camoAP":-1,"eq":"aucun","prt":"aucune","armor":0,"ap":6,"apLeft":-2,"oldapLeft":6,"salvoLeft":1,"ammo":"creuseur","ammo2":"none","vet":0,"xp":0,"range":0,"sort":0,"army":0,"tags":[]},{"id":162,"type":"Bugs","typeId":0,"team":"aliens","creaTurn":48,"loc":"zone","locId":0,"tileId":2835,"oldTileId":2956,"squadsLeft":6,"damage":0,"camoAP":-1,"eq":"aucun","prt":"aucune","armor":4,"ap":14,"apLeft":-2.9000000000000004,"oldapLeft":14,"salvoLeft":1,"ammo":"creuseur","ammo2":"none","vet":0,"xp":0,"range":0,"sort":0,"army":0,"tags":[]}]